[{"keys":{"boardId":"345c4a57dd22727f8d1da241af92d4b319c3b830","player1Id":"0b27623b24","player2Id":null},"turn":null,"winner":null,"board1":null,"status":"created"},{"keys":{"boardId":"280aaad3e1b0ce3c2af7085a70a0b6ce936a9c7b","player1Id":"bba3a2b664","player2Id":null},"turn":null,"winner":null,"board1":null,"status":"created"},{"keys":{"boardId":"5bf286fb02b76307e655590644ee5b57f9eb173f","player1Id":"d5c336db8d","player2Id":null},"turn":null,"winner":null,"board1":null,"status":"created"},{"keys":{"boardId":"4af2a0c2120ca4fad6ce4bd11493bc012721fbf1","player1Id":"51a8dbdb32","player2Id":null},"turn":null,"winner":null,"board1":null,"status":"created"},{"keys":{"boardId":"060fcb03b7fdec3a6f2c9ddf5123f16d4dcab56d","player1Id":"3871062843","player2Id":null},"turn":null,"winner":null,"board1":null,"status":"created"},{"keys":{"boardId":"5f89a4e2e3678fadf5c379a9452920ff954727f0","player1Id":"c668b77dbd","player2Id":null},"turn":null,"winner":null,"board1":[[null,null,"destroyer0","destroyer0",null,null,null,null,null,null],[null,null,null,null,null,"submarine1","submarine1","submarine1",null,null],[null,"cruiser2","cruiser2","cruiser2",null,null,null,null,null,null],[null,null,null,null,null,"battleship3","battleship3","battleship3","battleship3",null],[null,null,null,null,null,null,null,null,null,null],[null,"carrier4","carrier4","carrier4","carrier4","carrier4",null,null,null,null],[null,null,null,null,null,null,null,null,null,null],[null,null,null,null,null,null,null,null,null,null],[null,null,null,null,null,null,null,null,null,null],[null,null,null,null,null,null,null,null,null,null]],"status":"waiting","boats1":[2,3,3,4,5]},{"keys":{"boardId":"3ac58b79b56bc7c4bed8da200d953a520d06661c","player1Id":"c9a298669b","player2Id":null},"turn":null,"winner":null,"board1":null,"status":"created"},{"keys":{"boardId":"fb3269333418057c51012882c90250790a93eebb","player1Id":"a33aee995e","player2Id":null},"turn":null,"winner":null,"board1":null,"status":"created"},{"keys":{"boardId":"33ed0e6e454d42db608b0b8874403508c6271af7","player1Id":"7a07fd3495","player2Id":null},"turn":null,"winner":null,"board1":null,"status":"created"},{"keys":{"boardId":"b2718bb6359ebb0107ecafed1c731ed22e663395","player1Id":"04f2796cde","player2Id":null},"turn":null,"winner":null,"board1":[[null,null,null,null,null,null,null,null,null,null],[null,null,null,null,null,null,null,null,"destroyer0","destroyer0"],[null,null,null,null,null,null,null,null,null,null],[null,null,null,null,"submarine1","submarine1","submarine1",null,null,null],[null,null,null,null,null,null,null,null,null,null],[null,null,"battleship3","battleship3","battleship3","battleship3",null,null,null,null],[null,null,null,null,null,null,null,null,null,null],[null,null,null,"carrier4","carrier4","carrier4","carrier4","carrier4",null,null],[null,null,null,"cruiser2","cruiser2","cruiser2",null,null,null,null],[null,null,null,null,null,null,null,null,null,null]],"status":"waiting","boats1":[2,3,3,4,5]},{"keys":{"boardId":"12423a74a5313e862a8e5c4a2b44abf030ae47cf","player1Id":"6ca1340fc3","player2Id":null},"turn":null,"winner":null,"board1":null,"status":"created"},{"keys":{"boardId":"c60e04b44289df3777dbf165e1f3bfad86467b87","player1Id":"7a780b2e0b","player2Id":null},"turn":null,"winner":null,"board1":null,"status":"created"},{"keys":{"boardId":"ec22bc082c778071900012faf9d7b706ac535552","player1Id":"d1ba017088","player2Id":null},"turn":null,"winner":null,"board1":null,"status":"created"},{"keys":{"boardId":"7605859c45038ba1c6862c086a0e5e28429d47a9","player1Id":"5388108f92","player2Id":null},"turn":null,"winner":null,"board1":null,"status":"created"},{"keys":{"boardId":"eda02bdab2109e677e8c6144c383748d56016915","player1Id":"e65e807751","player2Id":null},"turn":null,"winner":null,"board1":null,"status":"created"},{"keys":{"boardId":"808f7fd4badac7a2bbebf7a4b7b059780ae80f54","player1Id":"8b9a1c5ea9","player2Id":null},"turn":null,"winner":null,"board1":null,"status":"created"},{"keys":{"boardId":"a37151dac94660d5283053530a0b7bb905460c1c","player1Id":"8876c92bcc","player2Id":null},"turn":null,"winner":null,"board1":null,"status":"created"},{"keys":{"boardId":"8b95ff8b405e8c1a48aff24568a7bab66d5df375","player1Id":"9c6787c139","player2Id":null},"turn":null,"winner":null,"board1":null,"status":"created"},{"keys":{"boardId":"9b3ad39ca70b454c08e65c7d3f579ff03712a552","player1Id":"041deb21c9","player2Id":null},"turn":null,"winner":null,"board1":null,"status":"created"},{"keys":{"boardId":"a1b354b6dd7344b59d264d85cc1d850cf32ca910","player1Id":"99c0a888c1","player2Id":null},"turn":null,"winner":null,"board1":null,"status":"created"},{"keys":{"boardId":"2993823b7fae26a1629f8187496cf1218324e5fd","player1Id":"71b14870a8","player2Id":null},"turn":null,"winner":null,"board1":null,"status":"created"},{"keys":{"boardId":"fb836bf5fac27862fede5aa27dd0a07fc08f19b6","player1Id":"0c805b8666","player2Id":null},"turn":null,"winner":null,"board1":null,"status":"created"},{"keys":{"boardId":"25fe89783ce565d2f61b72f20697156b954b78bd","player1Id":"5167789e57","player2Id":null},"turn":null,"winner":null,"board1":null,"status":"created"},{"keys":{"boardId":"28949dd3ab3cd670d73e6095c4e7bc93476606a1","player1Id":"558cfd213a","player2Id":null},"turn":null,"winner":null,"board1":null,"status":"created"},{"keys":{"boardId":"87c0dd27c9e091fb1c16e5da97832bdc9b75e054","player1Id":"6889ed2f36","player2Id":null},"turn":null,"winner":null,"board1":null,"status":"created"},{"keys":{"boardId":"d950f14aeb5f722c21e3fbda83b43ec2f840abed","player1Id":"8ad40cd5e7","player2Id":null},"turn":null,"winner":null,"board1":null,"status":"created"},{"keys":{"boardId":"fe9abe8ed8df55c4bdd6397e90317dbe10ff89d6","player2Id":"e1e9560d50"},"turn":"P1","winner":null,"board1":[[null,null,null,null,null,null,null,null,null,null],[null,"destroyer0","destroyer0",null,null,null,null,null,null,null],[null,null,null,null,"submarine1","submarine1","submarine1",null,null,null],["battleship3",null,null,null,null,null,null,null,null,null],["battleship3",null,null,null,null,null,null,null,"carrier4",null],["battleship3",null,null,null,null,null,null,null,"carrier4",null],["battleship3",null,"cruiser2","cruiser2","cruiser2",null,null,null,"carrier4",null],[null,null,null,null,null,null,null,null,"carrier4",null],[null,null,null,null,null,null,null,null,"carrier4",null],[null,null,null,null,null,null,null,null,null,null]],"status":"started","boats1":[2,3,3,4,5],"board2":[[null,null,null,null,null,null,null,null,null,null],[null,"destroyer0","destroyer0",null,null,null,null,null,null,null],[null,null,null,null,null,"submarine1","submarine1","submarine1",null,null],[null,null,null,null,null,null,null,null,null,null],[null,null,null,null,"cruiser2","cruiser2","cruiser2",null,null,null],[null,null,null,null,null,null,null,null,null,null],[null,null,"carrier4","carrier4","carrier4","carrier4","carrier4",null,null,null],[null,null,"battleship3","battleship3","battleship3","battleship3",null,null,null,null],[null,null,null,null,null,null,null,null,null,null],[null,null,null,null,null,null,null,null,null,null]],"boats2":[2,3,3,4,5]},{"keys":{"boardId":"8c6da94794339c0ec1883983cc6c948c46464f29","player2Id":"f8c37e2f18"},"turn":"P1","winner":null,"board1":[[null,null,null,null,null,null,null,null,null,null],["destroyer0","destroyer0",null,"submarine1","submarine1","submarine1",null,null,"carrier4",null],[null,null,null,null,null,null,null,null,"carrier4",null],[null,null,null,null,null,null,null,null,"carrier4",null],[null,null,"battleship3","battleship3","battleship3","battleship3",null,null,"carrier4",null],[null,null,null,null,null,null,null,null,"carrier4",null],[null,null,null,null,"cruiser2",null,null,null,null,null],[null,null,null,null,"cruiser2",null,null,null,null,null],[null,null,null,null,"cruiser2",null,null,null,null,null],[null,null,null,null,null,null,null,null,null,null]],"status":"started","boats1":[2,3,3,4,5],"board2":[[null,null,null,null,null,null,null,null,null,null],[null,null,null,null,"destroyer0","destroyer0",null,null,null,null],[null,null,null,null,null,null,null,null,null,null],[null,null,"cruiser2","cruiser2","cruiser2",null,null,null,null,null],[null,null,null,null,null,"submarine1","submarine1","submarine1",null,null],[null,null,null,null,null,null,null,null,null,null],[null,"carrier4","carrier4","carrier4","carrier4","carrier4",null,null,null,null],[null,null,null,null,"battleship3","battleship3","battleship3","battleship3",null,null],[null,null,null,null,null,null,null,null,null,null],[null,null,null,null,null,null,null,null,null,null]],"boats2":[2,3,3,4,5]},{"keys":{"boardId":"629baef87518c4d165c1c964e7c935d552c1f31d","player2Id":"8ab2e120a9"},"turn":null,"winner":null,"board1":null,"status":"joined","board2":null},{"keys":{"boardId":"dc0ca2fb9f9f63611aa041179368254ddca8d0ba","player2Id":"c6e6d0abb7"},"turn":"P1","winner":null,"board1":[[null,null,null,null,null,null,null,null,null,null],[null,null,null,null,null,null,"destroyer0","destroyer0",null,null],[null,null,"submarine1","submarine1","submarine1",null,null,null,null,null],[null,"carrier4",null,null,null,null,null,null,null,null],[null,"carrier4",null,null,null,null,"cruiser2","cruiser2","cruiser2",null],[null,"carrier4",null,null,null,null,null,null,null,null],[null,"carrier4",null,"battleship3","battleship3","battleship3","battleship3",null,null,null],[null,"carrier4",null,null,null,null,null,null,null,null],[null,null,null,null,null,null,null,null,null,null],[null,null,null,null,null,null,null,null,null,null]],"status":"started","boats1":[2,3,3,4,5],"board2":[[null,null,null,null,null,null,null,null,null,null],[null,"destroyer0","destroyer0",null,null,null,null,null,null,null],[null,null,null,null,"submarine1","submarine1","submarine1",null,null,null],[null,null,null,null,null,null,null,null,null,null],[null,"cruiser2","cruiser2","cruiser2",null,null,null,null,null,null],[null,null,null,null,null,null,"battleship3","battleship3","battleship3","battleship3"],[null,null,null,null,null,null,null,null,null,null],[null,null,"carrier4","carrier4","carrier4","carrier4","carrier4",null,null,null],[null,null,null,null,null,null,null,null,null,null],[null,null,null,null,null,null,null,null,null,null]],"boats2":[2,3,3,4,5]},{"keys":{"boardId":"2852f59cf6908055a79b1de7be91edc8d76f5815","player1Id":"62ad75c251","player2Id":"83ba56ba3d"},"turn":"P2","winner":null,"board1":[["O",null,null,null,"O",null,null,null,null,null],[null,null,null,null,"destroyer0","destroyer0",null,null,"carrier4",null],[null,null,null,null,null,null,null,null,"carrier4",null],[null,"submarine1","submarine1","submarine1",null,"O",null,null,"carrier4",null],[null,null,null,null,"O","X2","O",null,"carrier4",null],[null,null,null,null,null,"cruiser2",null,null,"carrier4",null],[null,null,null,null,null,"cruiser2",null,null,null,null],[null,null,null,null,null,null,null,null,null,null],[null,"battleship3","battleship3","battleship3","battleship3",null,null,null,null,null],[null,null,null,null,null,null,null,null,null,null]],"status":"started","boats1":[2,3,2,4,5],"board2":[[null,null,null,null,null,null,null,null,null,null],[null,null,null,null,null,"destroyer0","destroyer0",null,null,null],[null,null,null,null,null,null,null,null,null,null],[null,"submarine1","submarine1","submarine1",null,null,"O",null,null,null],[null,null,null,null,null,null,"cruiser2","cruiser2","cruiser2",null],[null,null,"F4",null,null,null,null,null,null,null],[null,null,"F4",null,null,null,null,null,null,null],[null,null,"F4",null,"battleship3","battleship3","X3","battleship3",null,null],[null,null,"F4",null,null,null,null,null,null,null],[null,null,"F4",null,null,null,null,null,null,null]],"boats2":[2,3,3,3,0]}]